cfntool/__init__.py
cfntool/botosession.py
cfntool/cfnclient.py
cfntool/errors.py
cfntool/installtemplate.py
cfntool-0.2.2.dist-info/entry_points.txt
cfntool-0.2.2.dist-info/WHEEL
cfntool-0.2.2.dist-info/METADATA
cfntool-0.2.2.dist-info/RECORD
