Metadata-Version: 2.1
Name: cfntool
Version: 0.2.2
Summary: Tool to Install and Delete Cloudformation stacks easily.
Home-page: https://github.com/ccdale/cfntool
License: GPL-3.0-or-later
Author: Chris Allison
Author-email: chris.charles.allison@gmail.com
Requires-Python: >=3.8,<4.0
Classifier: License :: OSI Approved :: GNU General Public License v3 or later (GPLv3+)
Classifier: Programming Language :: Python :: 3
Classifier: Programming Language :: Python :: 3.8
Requires-Dist: boto3 (>=1.12.15,<2.0.0)
Requires-Dist: ccalogging (>=0.3.3,<0.4.0)
Requires-Dist: chaim (>=0.8.0,<0.9.0)
Requires-Dist: getopt2 (>=0.0.3,<0.0.4)
Project-URL: Repository, https://github.com/ccdale/cfntool
